<?xml version="1.0"?>
<scene version="0.5.0">
  <integrator type="path">
    <integer name="maxDepth" value="-1" />
    <float name="rrThreshold" value="0.899999976" />
  </integrator>
  <sensor type="perspective">
    <float name="fov" value="39.3077011" />
    <string name="fovAxis" value="smaller" />
    <float name="nearClip" value="10" />
    <float name="farClip" value="2800" />
    <float name="focusDistance" value="1000" />
    <transform name="toWorld">
      <matrix value="-0.999259353, 0.000469412131, -0.0384802595, 278, -1.45519152e-11, 0.999925613, 0.0121978698, 273, 0.0384831205, 0.0121888341, -0.999184966, -800, 0, 0, 0, 1" />
    </transform>
    <film type="hdrfilm">
      <integer name="width" value="1280" />
      <integer name="height" value="720" />
    </film>
    <sampler type="ldsampler">
      <integer name="sampleCount" value="16" />
    </sampler>
  </sensor>
  <bsdf id="rtr_mat_2" type="diffuse">
    <spectrum name="reflectance" value="360:0.00793760642, 361:0.00810914673, 362:0.00828524493, 363:0.00846604165, 364:0.00865168497, 365:0.0088423267, 366:0.0090381233, 367:0.00923923776, 368:0.00944584049, 369:0.00965810474, 370:0.00987621117, 371:0.0101003498, 372:0.0103307124, 373:0.0105675012, 374:0.0108109247, 375:0.0110611981, 376:0.0113185467, 377:0.0115832025, 378:0.0118554048, 379:0.0121354042, 380:0.0124234576, 381:0.0127198342, 382:0.0130248107, 383:0.0133386757, 384:0.0136617282, 385:0.0139942765, 386:0.0143366428, 387:0.0146891586, 388:0.0150521705, 389:0.015426036, 390:0.0158111267, 391:0.0162078254, 392:0.0166165344, 393:0.0170376655, 394:0.0174716506, 395:0.0179189332, 396:0.0183799751, 397:0.0188552588, 398:0.0193452761, 399:0.0198505465, 400:0.0203716028, 401:0.0209090002, 402:0.0214633103, 403:0.0220351312, 404:0.0226250812, 405:0.0232337974, 406:0.0238619447, 407:0.0245102104, 408:0.025179306, 409:0.0258699711, 410:0.0265829694, 411:0.0273190904, 412:0.0280791558, 413:0.0288640112, 414:0.0296745375, 415:0.03051164, 416:0.0313762575, 417:0.0322693624, 418:0.0331919566, 419:0.0341450796, 420:0.0351297967, 421:0.0361472145, 422:0.0371984728, 423:0.0382847451, 424:0.0394072458, 425:0.0405672193, 426:0.0417659506, 427:0.0430047587, 428:0.0442849994, 429:0.045608066, 430:0.0469753891, 431:0.0483884364, 432:0.0498487018, 433:0.0513577238, 434:0.0529170707, 435:0.0545283407, 436:0.0561931655, 437:0.0579131991, 438:0.0596901365, 439:0.0615256764, 440:0.0634215549, 441:0.0653795227, 442:0.0674013346, 443:0.0694887638, 444:0.0716435984, 445:0.0738676041, 446:0.0761625618, 447:0.0785302371, 448:0.080972366, 449:0.0834906697, 450:0.0860868394, 451:0.0887625217, 452:0.0915193111, 453:0.0943587422, 454:0.097282283, 455:0.100291327, 456:0.10338717, 457:0.106570996, 458:0.109843887, 459:0.113206804, 460:0.11666055, 461:0.120205775, 462:0.123842984, 463:0.127572477, 464:0.131394386, 465:0.135308608, 466:0.139314845, 467:0.14341256, 468:0.147600964, 469:0.151879013, 470:0.15624541, 471:0.160698593, 472:0.165236682, 473:0.169857532, 474:0.174558699, 475:0.179337457, 476:0.18419075, 477:0.189115241, 478:0.194107279, 479:0.199162945, 480:0.204278022, 481:0.20944798, 482:0.214668065, 483:0.219933242, 484:0.225238234, 485:0.230577543, 486:0.235945448, 487:0.241336063, 488:0.246743292, 489:0.252160937, 490:0.257582635, 491:0.263001978, 492:0.268412411, 493:0.273807347, 494:0.279180229, 495:0.284524471, 496:0.289833426, 497:0.295100629, 498:0.300319612, 499:0.305483967, 500:0.310587466, 501:0.315623969, 502:0.320587456, 503:0.325472176, 504:0.330272406, 505:0.334982753, 506:0.339597881, 507:0.344112813, 508:0.348522633, 509:0.352822781, 510:0.357008815, 511:0.361076564, 512:0.365022093, 513:0.368841648, 514:0.372531742, 515:0.376089066, 516:0.379510552, 517:0.382793307, 518:0.385934681, 519:0.388932168, 520:0.391783535, 521:0.394486636, 522:0.397039503, 523:0.399440438, 524:0.401687801, 525:0.403780103, 526:0.405716032, 527:0.407494426, 528:0.409114182, 529:0.410574377, 530:0.411874175, 531:0.413012862, 532:0.413989842, 533:0.414804548, 534:0.415456563, 535:0.41594556, 536:0.416271269, 537:0.416433573, 538:0.416432351, 539:0.416267574, 540:0.415939391, 541:0.415447921, 542:0.414793462, 543:0.413976312, 544:0.412996918, 545:0.411855787, 546:0.410553545, 547:0.409090936, 548:0.407468766, 549:0.405688018, 550:0.403749704, 551:0.401655048, 552:0.39940539, 553:0.397002161, 554:0.394446969, 555:0.391741633, 556:0.388888061, 557:0.385888368, 558:0.382744849, 559:0.379459977, 560:0.376036435, 561:0.372477084, 562:0.368785024, 563:0.364963531, 564:0.361016154, 565:0.356946588, 566:0.352758795, 567:0.348456949, 568:0.34404549, 569:0.339529037, 570:0.334912419, 571:0.330200702, 572:0.325399131, 573:0.320513219, 574:0.315548539, 575:0.310510993, 576:0.305406541, 577:0.300241321, 578:0.295021564, 579:0.289753675, 580:0.284444124, 581:0.279099435, 582:0.273726165, 583:0.268330932, 584:0.26292032, 585:0.257500917, 586:0.252079219, 587:0.246661678, 588:0.241254658, 589:0.235864341, 590:0.230496824, 591:0.225157991, 592:0.21985355, 593:0.214589015, 594:0.209369645, 595:0.204200476, 596:0.199086279, 597:0.194031537, 598:0.189040482, 599:0.184117034, 600:0.179264843, 601:0.174487248, 602:0.169787258, 603:0.16516763, 604:0.160630807, 605:0.156178936, 606:0.15181385, 607:0.147537142, 608:0.143350109, 609:0.139253765, 610:0.135248914, 611:0.131336078, 612:0.127515569, 613:0.123787463, 614:0.120151646, 615:0.1166078, 616:0.113155432, 617:0.109793879, 618:0.106522337, 619:0.103339843, 620:0.100245327, 621:0.0972375795, 622:0.0943153128, 623:0.0914771408, 624:0.0887215808, 625:0.0860471129, 626:0.0834521279, 627:0.0809349865, 628:0.07849399, 629:0.0761274248, 630:0.073833555, 631:0.0716105998, 632:0.0694568008, 633:0.06737037, 634:0.0653495342, 635:0.0633925125, 636:0.0614975579, 637:0.0596629158, 638:0.0578868501, 639:0.0561676584, 640:0.0545036569, 641:0.0528931804, 642:0.0513346046, 643:0.0498263277, 644:0.048366785, 645:0.0469544418, 646:0.045587793, 647:0.044265382, 648:0.0429857783, 649:0.0417475849, 650:0.0405494459, 651:0.0393900461, 652:0.0382681042, 653:0.0371823646, 654:0.0361316241, 655:0.0351147093, 656:0.0341304764, 657:0.0331778228, 658:0.0322556831, 659:0.0313630141, 660:0.0304988176, 661:0.0296621229, 662:0.0288519897, 663:0.0280675143, 664:0.0273078158, 665:0.0265720505, 666:0.025859395, 667:0.0251690615, 668:0.0245002843, 669:0.023852326, 670:0.0232244767, 671:0.0226160493, 672:0.0220263768, 673:0.0214548241, 674:0.0209007729, 675:0.020363627, 676:0.0198428128, 677:0.019337777, 678:0.0188479852, 679:0.0183729213, 680:0.017912088, 681:0.0174650103, 682:0.0170312226, 683:0.0166102815, 684:0.0162017569, 685:0.0158052351, 686:0.0154203167, 687:0.0150466179, 688:0.0146837672, 689:0.0143314069, 690:0.0139891915, 691:0.0136567885, 692:0.0133338766, 693:0.0130201476, 694:0.0127153024, 695:0.0124190534, 696:0.0121311229, 697:0.0118512437, 698:0.0115791569, 699:0.0113146137, 700:0.0110573731, 701:0.0108072041, 702:0.0105638821, 703:0.010327192, 704:0.0100969244, 705:0.0098728789, 706:0.00965486094, 707:0.00944268331, 708:0.00923616532, 709:0.00903513189, 710:0.00883941445, 711:0.00864885002, 712:0.00846328028, 713:0.00828255527, 714:0.00810652692, 715:0.00793505367, 716:0.00776799908, 717:0.0076052295, 718:0.00744661829, 719:0.00729204062, 720:0.00714137778, 721:0.00699451426, 722:0.00685133785, 723:0.00671174098, 724:0.00657561887, 725:0.00644287094, 726:0.00631339895, 727:0.00618710881, 728:0.00606390927, 729:0.00594371138, 730:0.00582642993, 731:0.00571198203, 732:0.00560028711, 733:0.00549126836, 734:0.00538485032, 735:0.00528095989, 736:0.00517952722, 737:0.00508048339, 738:0.00498376321, 739:0.00488930242, 740:0.00479703862, 741:0.00470691221, 742:0.00461886497, 743:0.00453284057, 744:0.00444878452, 745:0.00436664326, 746:0.00428636605, 747:0.00420790305, 748:0.00413120538, 749:0.00405622739, 750:0.00398292299, 751:0.00391124794, 752:0.00384116033, 753:0.00377261802, 754:0.00370558142, 755:0.00364001095, 756:0.00357586937, 757:0.00351311965, 758:0.0034517264, 759:0.0033916547, 760:0.00333287101, 761:0.00327534298, 762:0.00321903871, 763:0.0031639277, 764:0.00310997991, 765:0.00305716624, 766:0.00300545897, 767:0.00295483018, 768:0.00290525332, 769:0.00285670301, 770:0.00280915364, 771:0.00276258122, 772:0.00271696178, 773:0.00267227204, 774:0.0026284901, 775:0.00258559361, 776:0.00254356163, 777:0.00250237365, 778:0.00246200943, 779:0.00242244964, 780:0.00238367496, 781:0.00234566722, 782:0.0023084085, 783:0.00227188109, 784:0.00223606825, 785:0.00220095296, 786:0.00216651964, 787:0.00213275221, 788:0.00209963578, 789:0.0020671552, 790:0.00203529582, 791:0.0020040439, 792:0.00197338569, 793:0.0019433077, 794:0.00191379676, 795:0.00188484043, 796:0.00185642624, 797:0.0018285421, 798:0.00180117635, 799:0.00177431758, 800:0.00174795452, 801:0.00172207644, 802:0.00169667264, 803:0.00167173287, 804:0.00164724712, 805:0.00162320537, 806:0.00159959833, 807:0.00157641643, 808:0.0015536506, 809:0.0015312921, 810:0.00150933221, 811:0.00148776243, 812:0.00146657473, 813:0.00144576072, 814:0.00142531283, 815:0.00140522339, 816:0.00138548482, 817:0.00136608991, 818:0.00134703144, 819:0.00132830266, 820:0.0013098967, 821:0.00129180681, 822:0.00127402681, 823:0.00125655008, 824:0.00123937067, 825:0.00122248253, 826:0.00120587985, 827:0.00118955667, 828:0.00117350766, 829:0.00115772709, 830:0.00114220975" />
  </bsdf>
  <bsdf id="rtr_mat_3" type="diffuse">
    <spectrum name="reflectance" value="360:0.426067233, 361:0.411623746, 362:0.397514492, 363:0.383763611, 364:0.37039116, 365:0.357413083, 366:0.34484154, 367:0.332685053, 368:0.32094869, 369:0.309634566, 370:0.298741877, 371:0.288267493, 372:0.27820611, 373:0.268550605, 374:0.259292334, 375:0.250421435, 376:0.241926998, 377:0.233797401, 378:0.226020455, 379:0.218583554, 380:0.211473897, 381:0.20467861, 382:0.198184803, 383:0.191979751, 384:0.186050907, 385:0.180385977, 386:0.174973011, 387:0.169800401, 388:0.164856896, 389:0.160131708, 390:0.155614406, 391:0.151295006, 392:0.147163957, 393:0.143212125, 394:0.139430806, 395:0.135811672, 396:0.132346839, 397:0.129028767, 398:0.12585035, 399:0.122804768, 400:0.119885616, 401:0.117086783, 402:0.11440248, 403:0.111827232, 404:0.109355852, 405:0.106983416, 406:0.104705267, 407:0.102517001, 408:0.100414433, 409:0.0983936191, 410:0.0964508131, 411:0.0945824608, 412:0.0927852169, 413:0.0910558924, 414:0.0893914774, 415:0.0877891183, 416:0.0862461179, 417:0.0847598985, 418:0.0833280385, 419:0.0819482356, 420:0.0806182995, 421:0.0793361664, 422:0.0780998543, 423:0.0769075081, 424:0.0757573545, 425:0.0746477097, 426:0.0735769719, 427:0.0725436285, 428:0.0715462267, 429:0.0705834106, 430:0.0696538612, 431:0.0687563419, 432:0.0678896829, 433:0.0670527518, 434:0.066244483, 435:0.0654638559, 436:0.0647099167, 437:0.0639817268, 438:0.0632784143, 439:0.0625991449, 440:0.0619431175, 441:0.061309576, 442:0.0606977977, 443:0.0601070933, 444:0.0595367998, 445:0.0589862913, 446:0.0584549755, 447:0.0579422787, 448:0.0574476533, 449:0.0569705889, 450:0.0565105826, 451:0.0560671687, 452:0.0556399003, 453:0.0552283414, 454:0.0548320897, 455:0.0544507541, 456:0.054083962, 457:0.0537313633, 458:0.0533926189, 459:0.0530674085, 460:0.0527554303, 461:0.0524563938, 462:0.0521700233, 463:0.0518960543, 464:0.0516342409, 465:0.0513843521, 466:0.0511461571, 467:0.0509194471, 468:0.0507040247, 469:0.0504997, 470:0.0503062941, 471:0.0501236431, 472:0.0499515906, 473:0.0497899838, 474:0.0496386886, 475:0.0494975746, 476:0.04936653, 477:0.0492454357, 478:0.0491341986, 479:0.0490327179, 480:0.0489409156, 481:0.0488587171, 482:0.0487860478, 483:0.048722852, 484:0.0486690775, 485:0.0486246794, 486:0.0485896245, 487:0.048563879, 488:0.0485474244, 489:0.0485402457, 490:0.0485423431, 491:0.0485537089, 492:0.048574362, 493:0.0486043096, 494:0.0486435853, 495:0.0486922152, 496:0.0487502404, 497:0.0488177128, 498:0.048894681, 499:0.0489812121, 500:0.0490773767, 501:0.0491832532, 502:0.0492989346, 503:0.0494245142, 504:0.0495600961, 505:0.0497057922, 506:0.0498617329, 507:0.050028041, 508:0.0502048694, 509:0.0503923595, 510:0.0505906753, 511:0.0507999957, 512:0.0510204919, 513:0.0512523688, 514:0.0514958203, 515:0.0517510734, 516:0.0520183481, 517:0.0522978902, 518:0.0525899529, 519:0.0528948009, 520:0.0532127209, 521:0.053544011, 522:0.0538889766, 523:0.0542479455, 524:0.0546212643, 525:0.0550092943, 526:0.0554124154, 527:0.0558310226, 528:0.056265533, 529:0.0567163862, 530:0.0571840443, 531:0.0576689802, 532:0.0581717081, 533:0.0586927496, 534:0.0592326671, 535:0.0597920418, 536:0.0603714809, 537:0.0609716251, 538:0.0615931526, 539:0.0622367635, 540:0.0629031956, 541:0.0635932311, 542:0.0643076748, 543:0.0650473982, 544:0.0658132806, 545:0.0666062757, 546:0.067427367, 547:0.0682775974, 548:0.0691580623, 549:0.0700699091, 550:0.0710143298, 551:0.0719926134, 552:0.0730060861, 553:0.0740561411, 554:0.075144276, 555:0.0762720257, 556:0.0774410293, 557:0.0786530226, 558:0.0799098015, 559:0.081213288, 560:0.0825655013, 561:0.08396855, 562:0.085424684, 563:0.0869362578, 564:0.0885057598, 565:0.0901358128, 566:0.0918292031, 567:0.0935888365, 568:0.0954178125, 569:0.0973193869, 570:0.0992969945, 571:0.101354279, 572:0.103495076, 573:0.105723433, 574:0.108043626, 575:0.110460192, 576:0.112977885, 577:0.115601756, 578:0.118337117, 579:0.121189594, 580:0.12416511, 581:0.127269909, 582:0.130510569, 583:0.133894056, 584:0.137427673, 585:0.141119108, 586:0.144976422, 587:0.14900814, 588:0.153223157, 589:0.157630786, 590:0.162240773, 591:0.167063311, 592:0.172108993, 593:0.177388817, 594:0.182914183, 595:0.188696891, 596:0.194749027, 597:0.201083004, 598:0.207711458, 599:0.214647219, 600:0.221903175, 601:0.229492173, 602:0.237426952, 603:0.245719954, 604:0.254383117, 605:0.263427794, 606:0.272864431, 607:0.282702386, 608:0.292949617, 609:0.3036125, 610:0.314695388, 611:0.326200426, 612:0.338127047, 613:0.350471944, 614:0.36322847, 615:0.376386523, 616:0.389932215, 617:0.403847784, 618:0.418111324, 619:0.432696849, 620:0.447574288, 621:0.462709606, 622:0.478065103, 623:0.493599743, 624:0.509269655, 625:0.525028646, 626:0.540828764, 627:0.556621313, 628:0.572357178, 629:0.5879879, 630:0.603466272, 631:0.618747115, 632:0.633787811, 633:0.64854902, 634:0.662994862, 635:0.677093625, 636:0.690817654, 637:0.704143763, 638:0.717052996, 639:0.729530573, 640:0.741566002, 641:0.753152549, 642:0.764286995, 643:0.774969399, 644:0.785202801, 645:0.794992685, 646:0.804346859, 647:0.81327486, 648:0.821787775, 649:0.829898059, 650:0.837618887, 651:0.844964266, 652:0.851948738, 653:0.858586907, 654:0.864893734, 655:0.870884001, 656:0.876572311, 657:0.881973147, 658:0.887100518, 659:0.891968131, 660:0.89658922, 661:0.900976539, 662:0.905142367, 663:0.909098387, 664:0.912855864, 665:0.916425526, 666:0.919817448, 667:0.923041403, 668:0.926106453, 669:0.929021418, 670:0.931794345, 671:0.934433162, 672:0.9369452, 673:0.939337254, 674:0.941615999, 675:0.943787515, 676:0.945857644, 677:0.94783181, 678:0.949715316, 679:0.951512873, 680:0.953229129, 681:0.954868376, 682:0.956434667, 683:0.957931876, 684:0.95936358, 685:0.960733116, 686:0.962043762, 687:0.9632985, 688:0.964500189, 689:0.965651453, 690:0.966754913, 691:0.967812836, 692:0.968827605, 693:0.969801188, 694:0.970735729, 695:0.971633017, 696:0.9724949, 697:0.973323047, 698:0.974119067, 699:0.97488445, 700:0.975620627, 701:0.976328969, 702:0.977010667, 703:0.977667034, 704:0.978299201, 705:0.978908241, 706:0.979495168, 707:0.980060995, 708:0.980606556, 709:0.981132865, 710:0.981640637, 711:0.982130766, 712:0.982603908, 713:0.983060896, 714:0.983502269, 715:0.98392874, 716:0.984340966, 717:0.984739482, 718:0.985124886, 719:0.985497653, 720:0.985858321, 721:0.986207366, 722:0.986545205, 723:0.986872375, 724:0.987189174, 725:0.987496138, 726:0.987793505, 727:0.988081753, 728:0.98836118, 729:0.988632083, 730:0.98889488, 731:0.989149749, 732:0.989397049, 733:0.989637077, 734:0.989870012, 735:0.990096211, 736:0.990315855, 737:0.99052918, 738:0.990736425, 739:0.990937769, 740:0.991133451, 741:0.991323709, 742:0.991508663, 743:0.99168849, 744:0.99186337, 745:0.992033541, 746:0.992199063, 747:0.992360175, 748:0.992516994, 749:0.992669582, 750:0.992818177, 751:0.992962897, 752:0.993103802, 753:0.993241131, 754:0.993374825, 755:0.99350518, 756:0.993632197, 757:0.993755996, 758:0.993876696, 759:0.993994355, 760:0.994109094, 761:0.994221032, 762:0.994330227, 763:0.994436741, 764:0.994540691, 765:0.994642079, 766:0.994741082, 767:0.994837701, 768:0.994932055, 769:0.995024145, 770:0.995114148, 771:0.995202005, 772:0.995287776, 773:0.99537164, 774:0.995453537, 775:0.995533586, 776:0.995611846, 777:0.995688319, 778:0.995763063, 779:0.995836139, 780:0.995907605, 781:0.995977461, 782:0.996045828, 783:0.996112645, 784:0.996178031, 785:0.996241987, 786:0.996304631, 787:0.996365845, 788:0.996425807, 789:0.996484458, 790:0.996541917, 791:0.996598125, 792:0.996653199, 793:0.996707082, 794:0.996759892, 795:0.996811569, 796:0.996862233, 797:0.996911824, 798:0.996960461, 799:0.997008026, 800:0.997054696, 801:0.997100413, 802:0.997145236, 803:0.997189164, 804:0.997232258, 805:0.997274458, 806:0.997315824, 807:0.997356415, 808:0.997396171, 809:0.997435212, 810:0.997473478, 811:0.997511029, 812:0.997547805, 813:0.997583985, 814:0.99761939, 815:0.9976542, 816:0.997688293, 817:0.997721791, 818:0.997754633, 819:0.99778688, 820:0.997818589, 821:0.997849643, 822:0.997880161, 823:0.997910142, 824:0.997939527, 825:0.997968435, 826:0.997996807, 827:0.998024702, 828:0.998052061, 829:0.998078942, 830:0.998105347" />
  </bsdf>
  <bsdf id="rtr_mat_1" type="diffuse">
    <spectrum name="reflectance" value="360:0.745892107, 361:0.745792031, 362:0.745692432, 363:0.745593369, 364:0.745494843, 365:0.745396793, 366:0.74529928, 367:0.745202303, 368:0.745105803, 369:0.74500978, 370:0.744914353, 371:0.744819403, 372:0.744724929, 373:0.744631052, 374:0.744537652, 375:0.744444788, 376:0.7443524, 377:0.74426055, 378:0.744169235, 379:0.744078457, 380:0.743988156, 381:0.743898392, 382:0.743809164, 383:0.743720412, 384:0.743632257, 385:0.743544579, 386:0.743457437, 387:0.743370831, 388:0.743284702, 389:0.74319917, 390:0.743114114, 391:0.743029594, 392:0.742945611, 393:0.742862165, 394:0.742779255, 395:0.742696822, 396:0.742614985, 397:0.742533624, 398:0.7424528, 399:0.742372513, 400:0.742292762, 401:0.742213547, 402:0.742134869, 403:0.742056727, 404:0.741979122, 405:0.741902053, 406:0.741825521, 407:0.741749525, 408:0.741674006, 409:0.741599083, 410:0.741524696, 411:0.741450846, 412:0.741377473, 413:0.741304696, 414:0.741232455, 415:0.74116075, 416:0.741089582, 417:0.741018951, 418:0.740948856, 419:0.740879297, 420:0.740810275, 421:0.740741789, 422:0.7406739, 423:0.740606487, 424:0.74053967, 425:0.74047339, 426:0.740407586, 427:0.740342379, 428:0.740277767, 429:0.740213633, 430:0.740150034, 431:0.740087032, 432:0.740024507, 433:0.739962578, 434:0.739901185, 435:0.739840388, 436:0.739780068, 437:0.739720345, 438:0.739661157, 439:0.739602506, 440:0.739544392, 441:0.739486814, 442:0.739429832, 443:0.739373386, 444:0.739317477, 445:0.739262164, 446:0.739207327, 447:0.739153087, 448:0.739099383, 449:0.739046276, 450:0.738993645, 451:0.73894161, 452:0.738890171, 453:0.738839209, 454:0.738788843, 455:0.738739014, 456:0.73868978, 457:0.738641083, 458:0.738592923, 459:0.738545299, 460:0.738498271, 461:0.738451779, 462:0.738405824, 463:0.738360465, 464:0.738315642, 465:0.738271415, 466:0.738227665, 467:0.738184571, 468:0.738141954, 469:0.738099933, 470:0.738058448, 471:0.738017559, 472:0.737977207, 473:0.737937391, 474:0.737898171, 475:0.737859488, 476:0.7378214, 477:0.737783849, 478:0.737746835, 479:0.737710416, 480:0.737674534, 481:0.737639248, 482:0.737604499, 483:0.737570286, 484:0.737536669, 485:0.737503648, 486:0.737471104, 487:0.737439215, 488:0.737407804, 489:0.737376988, 490:0.737346768, 491:0.737317085, 492:0.737287939, 493:0.737259388, 494:0.737231433, 495:0.737204015, 496:0.737177134, 497:0.737150848, 498:0.737125099, 499:0.737099946, 500:0.737075329, 501:0.737051249, 502:0.737027824, 503:0.737004876, 504:0.736982524, 505:0.736960769, 506:0.736939549, 507:0.736918926, 508:0.736898839, 509:0.736879289, 510:0.736860335, 511:0.736841977, 512:0.736824155, 513:0.736806929, 514:0.73679024, 515:0.736774087, 516:0.73675859, 517:0.736743569, 518:0.736729145, 519:0.736715317, 520:0.736702025, 521:0.736689329, 522:0.73667717, 523:0.736665606, 524:0.73665458, 525:0.736644149, 526:0.736634254, 527:0.736624956, 528:0.736616254, 529:0.736608088, 530:0.736600459, 531:0.736593425, 532:0.736586928, 533:0.736581087, 534:0.736575723, 535:0.736570954, 536:0.736566782, 537:0.736563146, 538:0.736560106, 539:0.736557603, 540:0.736555696, 541:0.736554325, 542:0.73655355, 543:0.736553311, 544:0.736553669, 545:0.736554563, 546:0.736556053, 547:0.736558139, 548:0.736560762, 549:0.736563981, 550:0.736567736, 551:0.736572027, 552:0.736576915, 553:0.736582398, 554:0.736588418, 555:0.736595035, 556:0.736602187, 557:0.736609936, 558:0.73661828, 559:0.736627102, 560:0.736636579, 561:0.736646593, 562:0.736657143, 563:0.736668289, 564:0.736680031, 565:0.736692309, 566:0.736705124, 567:0.736718535, 568:0.736732543, 569:0.736747086, 570:0.736762226, 571:0.736777902, 572:0.736794114, 573:0.736810982, 574:0.736828327, 575:0.736846268, 576:0.736864805, 577:0.736883879, 578:0.736903548, 579:0.736923754, 580:0.736944556, 581:0.736965895, 582:0.73698777, 583:0.7370103, 584:0.737033308, 585:0.737056911, 586:0.73708111, 587:0.737105846, 588:0.737131119, 589:0.737156987, 590:0.737183452, 591:0.737210453, 592:0.73723799, 593:0.737266123, 594:0.737294793, 595:0.737324059, 596:0.737353921, 597:0.73738426, 598:0.737415195, 599:0.737446725, 600:0.737478793, 601:0.737511396, 602:0.737544596, 603:0.737578392, 604:0.737612665, 605:0.737647593, 606:0.737682998, 607:0.737718999, 608:0.737755597, 609:0.73779273, 610:0.7378304, 611:0.737868607, 612:0.73790741, 613:0.737946808, 614:0.737986743, 615:0.738027215, 616:0.738068223, 617:0.738109827, 618:0.738152027, 619:0.738194704, 620:0.738238037, 621:0.738281846, 622:0.738326252, 623:0.738371193, 624:0.738416672, 625:0.738462746, 626:0.738509357, 627:0.738556564, 628:0.738604307, 629:0.738652587, 630:0.738701403, 631:0.738750815, 632:0.738800764, 633:0.738851249, 634:0.73890233, 635:0.738953948, 636:0.739006102, 637:0.739058793, 638:0.739112079, 639:0.739165902, 640:0.739220262, 641:0.739275217, 642:0.739330709, 643:0.739386737, 644:0.739443302, 645:0.739500463, 646:0.739558101, 647:0.739616334, 648:0.739675105, 649:0.739734471, 650:0.739794314, 651:0.739854753, 652:0.739915729, 653:0.739977241, 654:0.740039289, 655:0.740101933, 656:0.740165055, 657:0.740228772, 658:0.740293026, 659:0.740357816, 660:0.740423143, 661:0.740489066, 662:0.740555465, 663:0.740622461, 664:0.740689933, 665:0.740758002, 666:0.740826607, 667:0.740895748, 668:0.740965426, 669:0.74103564, 670:0.741106391, 671:0.741177678, 672:0.741249561, 673:0.741321921, 674:0.741394818, 675:0.74146831, 676:0.74154228, 677:0.741616845, 678:0.741691887, 679:0.741767466, 680:0.741843641, 681:0.741920292, 682:0.74199748, 683:0.742075264, 684:0.742153525, 685:0.742232323, 686:0.742311656, 687:0.742391527, 688:0.742471933, 689:0.742552876, 690:0.742634356, 691:0.742716312, 692:0.742798865, 693:0.742881894, 694:0.742965519, 695:0.743049622, 696:0.74313426, 697:0.743219435, 698:0.743305087, 699:0.743391335, 700:0.74347806, 701:0.743565321, 702:0.743653119, 703:0.743741453, 704:0.743830264, 705:0.743919671, 706:0.744009554, 707:0.744099915, 708:0.744190872, 709:0.744282305, 710:0.744374275, 711:0.744466722, 712:0.744559765, 713:0.744653285, 714:0.744747341, 715:0.744841874, 716:0.744936943, 717:0.745032549, 718:0.745128632, 719:0.745225251, 720:0.745322347, 721:0.745420039, 722:0.745518148, 723:0.745616853, 724:0.745716035, 725:0.745815694, 726:0.74591589, 727:0.746016622, 728:0.74611783, 729:0.746219575, 730:0.746321797, 731:0.746424496, 732:0.746527791, 733:0.746631503, 734:0.746735752, 735:0.746840537, 736:0.746945798, 737:0.747051537, 738:0.747157812, 739:0.747264564, 740:0.747371852, 741:0.747479618, 742:0.747587919, 743:0.747696638, 744:0.747805953, 745:0.747915685, 746:0.748025954, 747:0.748136699, 748:0.748247981, 749:0.74835968, 750:0.748471916, 751:0.748584688, 752:0.748697877, 753:0.748811603, 754:0.748925805, 755:0.749040484, 756:0.7491557, 757:0.749271393, 758:0.749387503, 759:0.749504149, 760:0.749621332, 761:0.749738932, 762:0.749857008, 763:0.749975622, 764:0.750094712, 765:0.750214279, 766:0.750334322, 767:0.750454783, 768:0.750575781, 769:0.750697315, 770:0.750819266, 771:0.750941694, 772:0.751064599, 773:0.75118798, 774:0.751311839, 775:0.751436174, 776:0.751560986, 777:0.751686275, 778:0.751812041, 779:0.751938283, 780:0.752065003, 781:0.75219214, 782:0.752319813, 783:0.752447903, 784:0.75257647, 785:0.752705514, 786:0.752835035, 787:0.752964973, 788:0.753095448, 789:0.75322634, 790:0.753357708, 791:0.753489554, 792:0.753621817, 793:0.753754556, 794:0.753887773, 795:0.754021406, 796:0.754155576, 797:0.754290104, 798:0.754425168, 799:0.754560649, 800:0.754696608, 801:0.754832983, 802:0.754969835, 803:0.755107105, 804:0.755244911, 805:0.755383074, 806:0.755521715, 807:0.755660832, 808:0.755800366, 809:0.755940378, 810:0.756080806, 811:0.756221652, 812:0.756362975, 813:0.756504774, 814:0.756646931, 815:0.756789625, 816:0.756932676, 817:0.757076204, 818:0.757220149, 819:0.757364571, 820:0.75750941, 821:0.757654667, 822:0.757800341, 823:0.757946491, 824:0.758093059, 825:0.758240044, 826:0.758387506, 827:0.758535326, 828:0.758683622, 829:0.758832335, 830:0.758981466" />
  </bsdf>
  <bsdf id="rtr_mat_0" type="diffuse">
    <spectrum name="reflectance" value="360:0.779999971, 361:0.779999971, 362:0.779999971, 363:0.779999971, 364:0.779999971, 365:0.779999971, 366:0.779999971, 367:0.779999971, 368:0.779999971, 369:0.779999971, 370:0.779999971, 371:0.779999971, 372:0.779999971, 373:0.779999971, 374:0.779999971, 375:0.779999971, 376:0.779999971, 377:0.779999971, 378:0.779999971, 379:0.779999971, 380:0.779999971, 381:0.779999971, 382:0.779999971, 383:0.779999971, 384:0.779999971, 385:0.779999971, 386:0.779999971, 387:0.779999971, 388:0.779999971, 389:0.779999971, 390:0.779999971, 391:0.779999971, 392:0.779999971, 393:0.779999971, 394:0.779999971, 395:0.779999971, 396:0.779999971, 397:0.779999971, 398:0.779999971, 399:0.779999971, 400:0.779999971, 401:0.779999971, 402:0.779999971, 403:0.779999971, 404:0.779999971, 405:0.779999971, 406:0.779999971, 407:0.779999971, 408:0.779999971, 409:0.779999971, 410:0.779999971, 411:0.779999971, 412:0.779999971, 413:0.779999971, 414:0.779999971, 415:0.779999971, 416:0.779999971, 417:0.779999971, 418:0.779999971, 419:0.779999971, 420:0.779999971, 421:0.779999971, 422:0.779999971, 423:0.779999971, 424:0.779999971, 425:0.779999971, 426:0.779999971, 427:0.779999971, 428:0.779999971, 429:0.779999971, 430:0.779999971, 431:0.779999971, 432:0.779999971, 433:0.779999971, 434:0.779999971, 435:0.779999971, 436:0.779999971, 437:0.779999971, 438:0.779999971, 439:0.779999971, 440:0.779999971, 441:0.779999971, 442:0.779999971, 443:0.779999971, 444:0.779999971, 445:0.779999971, 446:0.779999971, 447:0.779999971, 448:0.779999971, 449:0.779999971, 450:0.779999971, 451:0.779999971, 452:0.779999971, 453:0.779999971, 454:0.779999971, 455:0.779999971, 456:0.779999971, 457:0.779999971, 458:0.779999971, 459:0.779999971, 460:0.779999971, 461:0.779999971, 462:0.779999971, 463:0.779999971, 464:0.779999971, 465:0.779999971, 466:0.779999971, 467:0.779999971, 468:0.779999971, 469:0.779999971, 470:0.779999971, 471:0.779999971, 472:0.779999971, 473:0.779999971, 474:0.779999971, 475:0.779999971, 476:0.779999971, 477:0.779999971, 478:0.779999971, 479:0.779999971, 480:0.779999971, 481:0.779999971, 482:0.779999971, 483:0.779999971, 484:0.779999971, 485:0.779999971, 486:0.779999971, 487:0.779999971, 488:0.779999971, 489:0.779999971, 490:0.779999971, 491:0.779999971, 492:0.779999971, 493:0.779999971, 494:0.779999971, 495:0.779999971, 496:0.779999971, 497:0.779999971, 498:0.779999971, 499:0.779999971, 500:0.779999971, 501:0.779999971, 502:0.779999971, 503:0.779999971, 504:0.779999971, 505:0.779999971, 506:0.779999971, 507:0.779999971, 508:0.779999971, 509:0.779999971, 510:0.779999971, 511:0.779999971, 512:0.779999971, 513:0.779999971, 514:0.779999971, 515:0.779999971, 516:0.779999971, 517:0.779999971, 518:0.779999971, 519:0.779999971, 520:0.779999971, 521:0.779999971, 522:0.779999971, 523:0.779999971, 524:0.779999971, 525:0.779999971, 526:0.779999971, 527:0.779999971, 528:0.779999971, 529:0.779999971, 530:0.779999971, 531:0.779999971, 532:0.779999971, 533:0.779999971, 534:0.779999971, 535:0.779999971, 536:0.779999971, 537:0.779999971, 538:0.779999971, 539:0.779999971, 540:0.779999971, 541:0.779999971, 542:0.779999971, 543:0.779999971, 544:0.779999971, 545:0.779999971, 546:0.779999971, 547:0.779999971, 548:0.779999971, 549:0.779999971, 550:0.779999971, 551:0.779999971, 552:0.779999971, 553:0.779999971, 554:0.779999971, 555:0.779999971, 556:0.779999971, 557:0.779999971, 558:0.779999971, 559:0.779999971, 560:0.779999971, 561:0.779999971, 562:0.779999971, 563:0.779999971, 564:0.779999971, 565:0.779999971, 566:0.779999971, 567:0.779999971, 568:0.779999971, 569:0.779999971, 570:0.779999971, 571:0.779999971, 572:0.779999971, 573:0.779999971, 574:0.779999971, 575:0.779999971, 576:0.779999971, 577:0.779999971, 578:0.779999971, 579:0.779999971, 580:0.779999971, 581:0.779999971, 582:0.779999971, 583:0.779999971, 584:0.779999971, 585:0.779999971, 586:0.779999971, 587:0.779999971, 588:0.779999971, 589:0.779999971, 590:0.779999971, 591:0.779999971, 592:0.779999971, 593:0.779999971, 594:0.779999971, 595:0.779999971, 596:0.779999971, 597:0.779999971, 598:0.779999971, 599:0.779999971, 600:0.779999971, 601:0.779999971, 602:0.779999971, 603:0.779999971, 604:0.779999971, 605:0.779999971, 606:0.779999971, 607:0.779999971, 608:0.779999971, 609:0.779999971, 610:0.779999971, 611:0.779999971, 612:0.779999971, 613:0.779999971, 614:0.779999971, 615:0.779999971, 616:0.779999971, 617:0.779999971, 618:0.779999971, 619:0.779999971, 620:0.779999971, 621:0.779999971, 622:0.779999971, 623:0.779999971, 624:0.779999971, 625:0.779999971, 626:0.779999971, 627:0.779999971, 628:0.779999971, 629:0.779999971, 630:0.779999971, 631:0.779999971, 632:0.779999971, 633:0.779999971, 634:0.779999971, 635:0.779999971, 636:0.779999971, 637:0.779999971, 638:0.779999971, 639:0.779999971, 640:0.779999971, 641:0.779999971, 642:0.779999971, 643:0.779999971, 644:0.779999971, 645:0.779999971, 646:0.779999971, 647:0.779999971, 648:0.779999971, 649:0.779999971, 650:0.779999971, 651:0.779999971, 652:0.779999971, 653:0.779999971, 654:0.779999971, 655:0.779999971, 656:0.779999971, 657:0.779999971, 658:0.779999971, 659:0.779999971, 660:0.779999971, 661:0.779999971, 662:0.779999971, 663:0.779999971, 664:0.779999971, 665:0.779999971, 666:0.779999971, 667:0.779999971, 668:0.779999971, 669:0.779999971, 670:0.779999971, 671:0.779999971, 672:0.779999971, 673:0.779999971, 674:0.779999971, 675:0.779999971, 676:0.779999971, 677:0.779999971, 678:0.779999971, 679:0.779999971, 680:0.779999971, 681:0.779999971, 682:0.779999971, 683:0.779999971, 684:0.779999971, 685:0.779999971, 686:0.779999971, 687:0.779999971, 688:0.779999971, 689:0.779999971, 690:0.779999971, 691:0.779999971, 692:0.779999971, 693:0.779999971, 694:0.779999971, 695:0.779999971, 696:0.779999971, 697:0.779999971, 698:0.779999971, 699:0.779999971, 700:0.779999971, 701:0.779999971, 702:0.779999971, 703:0.779999971, 704:0.779999971, 705:0.779999971, 706:0.779999971, 707:0.779999971, 708:0.779999971, 709:0.779999971, 710:0.779999971, 711:0.779999971, 712:0.779999971, 713:0.779999971, 714:0.779999971, 715:0.779999971, 716:0.779999971, 717:0.779999971, 718:0.779999971, 719:0.779999971, 720:0.779999971, 721:0.779999971, 722:0.779999971, 723:0.779999971, 724:0.779999971, 725:0.779999971, 726:0.779999971, 727:0.779999971, 728:0.779999971, 729:0.779999971, 730:0.779999971, 731:0.779999971, 732:0.779999971, 733:0.779999971, 734:0.779999971, 735:0.779999971, 736:0.779999971, 737:0.779999971, 738:0.779999971, 739:0.779999971, 740:0.779999971, 741:0.779999971, 742:0.779999971, 743:0.779999971, 744:0.779999971, 745:0.779999971, 746:0.779999971, 747:0.779999971, 748:0.779999971, 749:0.779999971, 750:0.779999971, 751:0.779999971, 752:0.779999971, 753:0.779999971, 754:0.779999971, 755:0.779999971, 756:0.779999971, 757:0.779999971, 758:0.779999971, 759:0.779999971, 760:0.779999971, 761:0.779999971, 762:0.779999971, 763:0.779999971, 764:0.779999971, 765:0.779999971, 766:0.779999971, 767:0.779999971, 768:0.779999971, 769:0.779999971, 770:0.779999971, 771:0.779999971, 772:0.779999971, 773:0.779999971, 774:0.779999971, 775:0.779999971, 776:0.779999971, 777:0.779999971, 778:0.779999971, 779:0.779999971, 780:0.779999971, 781:0.779999971, 782:0.779999971, 783:0.779999971, 784:0.779999971, 785:0.779999971, 786:0.779999971, 787:0.779999971, 788:0.779999971, 789:0.779999971, 790:0.779999971, 791:0.779999971, 792:0.779999971, 793:0.779999971, 794:0.779999971, 795:0.779999971, 796:0.779999971, 797:0.779999971, 798:0.779999971, 799:0.779999971, 800:0.779999971, 801:0.779999971, 802:0.779999971, 803:0.779999971, 804:0.779999971, 805:0.779999971, 806:0.779999971, 807:0.779999971, 808:0.779999971, 809:0.779999971, 810:0.779999971, 811:0.779999971, 812:0.779999971, 813:0.779999971, 814:0.779999971, 815:0.779999971, 816:0.779999971, 817:0.779999971, 818:0.779999971, 819:0.779999971, 820:0.779999971, 821:0.779999971, 822:0.779999971, 823:0.779999971, 824:0.779999971, 825:0.779999971, 826:0.779999971, 827:0.779999971, 828:0.779999971, 829:0.779999971, 830:0.779999971" />
  </bsdf>
  <shape type="obj" id="cbox_light">
    <string name="filename" value="meshes/cbox_light.obj" />
    <transform name="toWorld">
      <matrix value="1, 0, 0, 0, 0, 1, 0, -0.5, 0, 0, 1, 0, 0, 0, 0, 1" />
    </transform>
    <ref id="rtr_mat_0" />
    <emitter type="area">
      <spectrum name="radiance" value="400:0, 500:8, 600:15.6000004, 700:18.3999996" />
    </emitter>
  </shape>
  <shape type="obj" id="cbox_floor">
    <string name="filename" value="meshes/cbox_floor.obj" />
    <transform name="toWorld">
      <matrix value="1, 0, 0, 0, 0, 1, 0, 0, 0, 0, 1, 0, 0, 0, 0, 1" />
    </transform>
    <ref id="rtr_mat_1" />
  </shape>
  <shape type="obj" id="cbox_ceiling">
    <string name="filename" value="meshes/cbox_ceiling.obj" />
    <transform name="toWorld">
      <matrix value="1, 0, 0, 0, 0, 1, 0, 0, 0, 0, 1, 0, 0, 0, 0, 1" />
    </transform>
    <ref id="rtr_mat_1" />
  </shape>
  <shape type="obj" id="cbox_back">
    <string name="filename" value="meshes/cbox_back.obj" />
    <transform name="toWorld">
      <matrix value="1, 0, 0, 0, 0, 1, 0, 0, 0, 0, 1, 0, 0, 0, 0, 1" />
    </transform>
    <ref id="rtr_mat_1" />
  </shape>
  <shape type="obj" id="cbox_greenwall">
    <string name="filename" value="meshes/cbox_greenwall.obj" />
    <transform name="toWorld">
      <matrix value="1, 0, 0, 0, 0, 1, 0, 0, 0, 0, 1, 0, 0, 0, 0, 1" />
    </transform>
    <ref id="rtr_mat_2" />
  </shape>
  <shape type="obj" id="cbox_redwall">
    <string name="filename" value="meshes/cbox_redwall.obj" />
    <transform name="toWorld">
      <matrix value="1, 0, 0, 0, 0, 1, 0, 0, 0, 0, 1, 0, 0, 0, 0, 1" />
    </transform>
    <ref id="rtr_mat_3" />
  </shape>
  <shape type="obj" id="cbox_smallbox">
    <string name="filename" value="meshes/cbox_smallbox.obj" />
    <transform name="toWorld">
      <matrix value="1, 0, 0, 0, 0, 1, 0, 0, 0, 0, 1, 0, 0, 0, 0, 1" />
    </transform>
    <ref id="rtr_mat_1" />
  </shape>
  <shape type="obj" id="cbox_largebox">
    <string name="filename" value="meshes/cbox_largebox.obj" />
    <transform name="toWorld">
      <matrix value="1, 0, 0, 0, 0, 1, 0, 0, 0, 0, 1, 0, 0, 0, 0, 1" />
    </transform>
    <ref id="rtr_mat_1" />
  </shape>
</scene>
